chat_mcp/__init__.py
chat_mcp/ai_provider.py
chat_mcp/easy_chat.py
chat_mcp/ipc_handler.py
chat_mcp/mcp_chat_handler.py
chat_mcp/mcp_service.py
chat_mcp/mcp_types.py
chat_mcp-0.1.1.dist-info/METADATA
chat_mcp-0.1.1.dist-info/WHEEL
chat_mcp-0.1.1.dist-info/entry_points.txt
chat_mcp-0.1.1.dist-info/RECORD
