Metadata-Version: 2.4
Name: chat-mcp
Version: 0.1.1
Summary: MCP客户端库，用于在对话中调用MCP工具
Requires-Python: >=3.11
Requires-Dist: asyncio-mqtt>=0.16.0
Requires-Dist: litellm>=1.0.0
Requires-Dist: mcp[cli]>=1.0.0
Requires-Dist: pydantic>=2.0.0
Requires-Dist: python-dotenv>=1.0.0
Requires-Dist: setuptools>=80.9.0
Provides-Extra: dev
Requires-Dist: black>=23.0.0; extra == 'dev'
Requires-Dist: pytest-asyncio>=0.21.0; extra == 'dev'
Requires-Dist: pytest>=7.0.0; extra == 'dev'
Requires-Dist: ruff>=0.1.0; extra == 'dev'
